Metadata-Version: 1.1
Name: UTG
Version: 0.3.2
Summary: Генератор связанного русского текста
Home-page: https://github.com/Tiendil/utg
Author: Aleksey Yeletsky <Tiendil>
Author-email: a.eletsky@gmail.com
License: BSD
Keywords: text generation,генерация текста
Platform: UNKNOWN
Classifier: Development Status :: 4 - Beta
Classifier: Intended Audience :: Developers
Classifier: Topic :: Software Development :: Libraries :: Python Modules
Classifier: License :: OSI Approved :: BSD License
Classifier: Programming Language :: Python :: 3
Classifier: Programming Language :: Python :: 3.5
Classifier: Programming Language :: Python :: 3.6
Classifier: Programming Language :: Python :: 3.7
Classifier: Programming Language :: Python :: 3.8
Classifier: Natural Language :: Russian
